{
 "1106175308099698688": {
  "Lang": "en", 
  "Place": null, 
  "User": {
   "follow_request_sent": false, 
   "has_extended_profile": false, 
   "profile_use_background_image": true, 
   "default_profile_image": false, 
   "id": 1086065136316674048, 
   "profile_background_image_url_https": null, 
   "verified": false, 
   "translator_type": "none", 
   "profile_text_color": "333333", 
   "profile_image_url_https": "https://pbs.twimg.com/profile_images/1104922089750970369/u5EBWlsF_normal.jpg", 
   "profile_sidebar_fill_color": "DDEEF6", 
   "entities": {
    "description": {
     "urls": []
    }
   }, 
   "followers_count": 25, 
   "profile_sidebar_border_color": "C0DEED", 
   "id_str": "1086065136316674048", 
   "profile_background_color": "F5F8FA", 
   "listed_count": 0, 
   "is_translation_enabled": false, 
   "utc_offset": null, 
   "statuses_count": 1396, 
   "description": "OT4 \ud83d\udc96 - BLACKPINK IS MY LIFE \ud83d\ude48\ud83d\udc90", 
   "friends_count": 285, 
   "location": "Ecuador ", 
   "profile_link_color": "1DA1F2", 
   "profile_image_url": "http://pbs.twimg.com/profile_images/1104922089750970369/u5EBWlsF_normal.jpg", 
   "following": false, 
   "geo_enabled": false, 
   "profile_banner_url": "https://pbs.twimg.com/profile_banners/1086065136316674048/1549050429", 
   "profile_background_image_url": null, 
   "screen_name": "jenlisaxforever", 
   "lang": "en", 
   "profile_background_tile": false, 
   "favourites_count": 291, 
   "name": "BLACKPINK IS LIFE \ud83d\udc96", 
   "notifications": false, 
   "url": null, 
   "created_at": "Fri Jan 18 00:58:01 +0000 2019", 
   "contributors_enabled": false, 
   "time_zone": null, 
   "protected": false, 
   "default_profile": true, 
   "is_translator": false
  }, 
  "Title": "Homeland", 
  "Date": "Thu Mar 14 12:48:39 +0000 2019", 
  "Text": "RT @with_lalice: You should be ashamed of Lisabar @FROMREALYG, they promote Lisa everywhere, and you don't even promote Lisa in her homelan\u2026", 
  "Hashtags": {
   "symbols": [], 
   "user_mentions": [
    {
     "id": 941132777163964417, 
     "indices": [
      3, 
      15
     ], 
     "id_str": "941132777163964417", 
     "screen_name": "with_lalice", 
     "name": "Winter\u2744\ufe0f"
    }, 
    {
     "id": 765798249785597952, 
     "indices": [
      50, 
      61
     ], 
     "id_str": "765798249785597952", 
     "screen_name": "FROMREALYG", 
     "name": "FROM YG"
    }
   ], 
   "hashtags": [], 
   "urls": []
  }, 
  "Geo": null
 }, 
 "1106175337669365761": {
  "Lang": "en", 
  "Place": null, 
  "User": {
   "follow_request_sent": false, 
   "has_extended_profile": false, 
   "profile_use_background_image": true, 
   "default_profile_image": false, 
   "id": 2513031223, 
   "profile_background_image_url_https": "https://abs.twimg.com/images/themes/theme1/bg.png", 
   "verified": false, 
   "translator_type": "none", 
   "profile_text_color": "333333", 
   "profile_image_url_https": "https://pbs.twimg.com/profile_images/1098485179138564097/-Lm1XugP_normal.jpg", 
   "profile_sidebar_fill_color": "DDEEF6", 
   "entities": {
    "description": {
     "urls": []
    }
   }, 
   "followers_count": 191, 
   "profile_sidebar_border_color": "C0DEED", 
   "id_str": "2513031223", 
   "profile_background_color": "C0DEED", 
   "listed_count": 11, 
   "is_translation_enabled": false, 
   "utc_offset": null, 
   "statuses_count": 11694, 
   "description": "Doing my bit for the nation given to me.\nJai Hind.....", 
   "friends_count": 279, 
   "location": "mumbai", 
   "profile_link_color": "1DA1F2", 
   "profile_image_url": "http://pbs.twimg.com/profile_images/1098485179138564097/-Lm1XugP_normal.jpg", 
   "following": false, 
   "geo_enabled": false, 
   "profile_banner_url": "https://pbs.twimg.com/profile_banners/2513031223/1546868717", 
   "profile_background_image_url": "http://abs.twimg.com/images/themes/theme1/bg.png", 
   "screen_name": "dpkepf", 
   "lang": "en", 
   "profile_background_tile": false, 
   "favourites_count": 8300, 
   "name": "Deepak Kumar", 
   "notifications": false, 
   "url": null, 
   "created_at": "Wed May 21 16:24:48 +0000 2014", 
   "contributors_enabled": false, 
   "time_zone": null, 
   "protected": false, 
   "default_profile": true, 
   "is_translator": false
  }, 
  "Title": "Homeland", 
  "Date": "Thu Mar 14 12:48:46 +0000 2019", 
  "Text": "RT @amritabhinder: Masood Azhar is a terrorist!\n\nDalai Lama is a Nobel Peace Prize laureate, just like Malala.\n\nPS: He was awarded Nobel Pe\u2026", 
  "Hashtags": {
   "symbols": [], 
   "user_mentions": [
    {
     "id": 37396883, 
     "indices": [
      3, 
      17
     ], 
     "id_str": "37396883", 
     "screen_name": "amritabhinder", 
     "name": "Amrita Bhinder"
    }
   ], 
   "hashtags": [], 
   "urls": []
  }, 
  "Geo": null
 }, 
 "1106175314701545475": {
  "Lang": "en", 
  "Place": null, 
  "User": {
   "follow_request_sent": false, 
   "has_extended_profile": false, 
   "profile_use_background_image": true, 
   "default_profile_image": false, 
   "id": 131511674, 
   "profile_background_image_url_https": "https://abs.twimg.com/images/themes/theme1/bg.png", 
   "verified": false, 
   "translator_type": "none", 
   "profile_text_color": "333333", 
   "profile_image_url_https": "https://pbs.twimg.com/profile_images/1066779380943343616/IEBFSluK_normal.jpg", 
   "profile_sidebar_fill_color": "DDEEF6", 
   "entities": {
    "description": {
     "urls": []
    }
   }, 
   "followers_count": 204, 
   "profile_sidebar_border_color": "C0DEED", 
   "id_str": "131511674", 
   "profile_background_color": "C0DEED", 
   "listed_count": 27, 
   "is_translation_enabled": false, 
   "utc_offset": null, 
   "statuses_count": 57416, 
   "description": "Expect logical questions. If you do not acknowledge the problem, you can never address it. \nLove travelling", 
   "friends_count": 559, 
   "location": "Maryland, USA", 
   "profile_link_color": "1DA1F2", 
   "profile_image_url": "http://pbs.twimg.com/profile_images/1066779380943343616/IEBFSluK_normal.jpg", 
   "following": false, 
   "geo_enabled": true, 
   "profile_banner_url": "https://pbs.twimg.com/profile_banners/131511674/1493468880", 
   "profile_background_image_url": "http://abs.twimg.com/images/themes/theme1/bg.png", 
   "screen_name": "rajgrad", 
   "lang": "en", 
   "profile_background_tile": false, 
   "favourites_count": 51407, 
   "name": "raj", 
   "notifications": false, 
   "url": null, 
   "created_at": "Sat Apr 10 13:58:30 +0000 2010", 
   "contributors_enabled": false, 
   "time_zone": null, 
   "protected": false, 
   "default_profile": true, 
   "is_translator": false
  }, 
  "Title": "Homeland", 
  "Date": "Thu Mar 14 12:48:41 +0000 2019", 
  "Text": "RT @amritabhinder: Masood Azhar is a terrorist!\n\nDalai Lama is a Nobel Peace Prize laureate, just like Malala.\n\nPS: He was awarded Nobel Pe\u2026", 
  "Hashtags": {
   "symbols": [], 
   "user_mentions": [
    {
     "id": 37396883, 
     "indices": [
      3, 
      17
     ], 
     "id_str": "37396883", 
     "screen_name": "amritabhinder", 
     "name": "Amrita Bhinder"
    }
   ], 
   "hashtags": [], 
   "urls": []
  }, 
  "Geo": null
 }, 
 "1106175294791139328": {
  "Lang": "en", 
  "Place": null, 
  "User": {
   "follow_request_sent": false, 
   "has_extended_profile": false, 
   "profile_use_background_image": true, 
   "default_profile_image": false, 
   "id": 2891822077, 
   "profile_background_image_url_https": "https://abs.twimg.com/images/themes/theme1/bg.png", 
   "verified": false, 
   "translator_type": "none", 
   "profile_text_color": "333333", 
   "profile_image_url_https": "https://pbs.twimg.com/profile_images/530223215696961536/qi75gzBs_normal.jpeg", 
   "profile_sidebar_fill_color": "DDEEF6", 
   "entities": {
    "description": {
     "urls": []
    }
   }, 
   "followers_count": 97, 
   "profile_sidebar_border_color": "C0DEED", 
   "id_str": "2891822077", 
   "profile_background_color": "C0DEED", 
   "listed_count": 7, 
   "is_translation_enabled": false, 
   "utc_offset": null, 
   "statuses_count": 5067, 
   "description": "", 
   "friends_count": 267, 
   "location": "", 
   "profile_link_color": "1DA1F2", 
   "profile_image_url": "http://pbs.twimg.com/profile_images/530223215696961536/qi75gzBs_normal.jpeg", 
   "following": false, 
   "geo_enabled": false, 
   "profile_background_image_url": "http://abs.twimg.com/images/themes/theme1/bg.png", 
   "screen_name": "stuckinmotion", 
   "lang": "en", 
   "profile_background_tile": false, 
   "favourites_count": 7062, 
   "name": "Rod Q", 
   "notifications": false, 
   "url": null, 
   "created_at": "Thu Nov 06 04:57:21 +0000 2014", 
   "contributors_enabled": false, 
   "time_zone": null, 
   "protected": false, 
   "default_profile": true, 
   "is_translator": false
  }, 
  "Title": "Homeland", 
  "Date": "Thu Mar 14 12:48:36 +0000 2019", 
  "Text": "RT @DavidMuellerRMK: Nadhem is living in the camp with his family and 17,000 other #Yazidis since 2014 &amp; has almost lost hope of returning\u2026", 
  "Hashtags": {
   "symbols": [], 
   "user_mentions": [
    {
     "id": 302018356, 
     "indices": [
      3, 
      19
     ], 
     "id_str": "302018356", 
     "screen_name": "DavidMuellerRMK", 
     "name": "David M\u00fcller"
    }
   ], 
   "hashtags": [
    {
     "indices": [
      83, 
      91
     ], 
     "text": "Yazidis"
    }
   ], 
   "urls": []
  }, 
  "Geo": null
 }, 
 "1106175236192391168": {
  "Lang": "en", 
  "Place": null, 
  "User": {
   "follow_request_sent": false, 
   "has_extended_profile": false, 
   "profile_use_background_image": false, 
   "default_profile_image": false, 
   "id": 888750286751358976, 
   "profile_background_image_url_https": "https://abs.twimg.com/images/themes/theme1/bg.png", 
   "verified": false, 
   "translator_type": "none", 
   "profile_text_color": "000000", 
   "profile_image_url_https": "https://pbs.twimg.com/profile_images/891346644507164673/uW_-Rit7_normal.jpg", 
   "profile_sidebar_fill_color": "000000", 
   "entities": {
    "url": {
     "urls": [
      {
       "url": "https://t.co/NZYRNkhuvZ", 
       "indices": [
        0, 
        23
       ], 
       "expanded_url": "http://LaDonnaRae1961.blogspot.com", 
       "display_url": "LaDonnaRae1961.blogspot.com"
      }
     ]
    }, 
    "description": {
     "urls": []
    }
   }, 
   "followers_count": 4076, 
   "profile_sidebar_border_color": "000000", 
   "id_str": "888750286751358976", 
   "profile_background_color": "000000", 
   "listed_count": 23, 
   "is_translation_enabled": false, 
   "utc_offset": null, 
   "statuses_count": 179314, 
   "description": "Certified Intelligence Analyst.   USAF veteran. Daughter of a Master Chief. \"Follow\" at your own risk. \ud83d\ude08", 
   "friends_count": 4877, 
   "location": "https://www.udemy.com/certificate/UC-H0UBINXI/?utm_campaign=email&utm_source=sendgrid.com&utm_medium=email", 
   "profile_link_color": "1B95E0", 
   "profile_image_url": "http://pbs.twimg.com/profile_images/891346644507164673/uW_-Rit7_normal.jpg", 
   "following": false, 
   "geo_enabled": false, 
   "profile_banner_url": "https://pbs.twimg.com/profile_banners/888750286751358976/1503064759", 
   "profile_background_image_url": "http://abs.twimg.com/images/themes/theme1/bg.png", 
   "screen_name": "PizzaGateLibya", 
   "lang": "en", 
   "profile_background_tile": false, 
   "favourites_count": 12684, 
   "name": "Stop #FBI Corruption", 
   "notifications": false, 
   "url": "https://t.co/NZYRNkhuvZ", 
   "created_at": "Sat Jul 22 13:19:15 +0000 2017", 
   "contributors_enabled": false, 
   "time_zone": null, 
   "protected": false, 
   "default_profile": false, 
   "is_translator": false
  }, 
  "Title": "Homeland", 
  "Date": "Thu Mar 14 12:48:22 +0000 2019", 
  "Text": "@angloyankdad @emmacpicken @AyoCaesar @MrhobanJames @Husker_Ju @alexrubner @jobellerina @moose_malloy @AbiWilks\u2026 https://t.co/UH4m34f66y", 
  "Hashtags": {
   "symbols": [], 
   "user_mentions": [
    {
     "id": 880964721666666496, 
     "indices": [
      0, 
      13
     ], 
     "id_str": "880964721666666496", 
     "screen_name": "angloyankdad", 
     "name": "AngloAmericanDad"
    }, 
    {
     "id": 1346629159, 
     "indices": [
      14, 
      26
     ], 
     "id_str": "1346629159", 
     "screen_name": "emmacpicken", 
     "name": "Emma Picken."
    }, 
    {
     "id": 619050616, 
     "indices": [
      27, 
      37
     ], 
     "id_str": "619050616", 
     "screen_name": "AyoCaesar", 
     "name": "Ash Sarkar"
    }, 
    {
     "id": 3003886007, 
     "indices": [
      38, 
      51
     ], 
     "id_str": "3003886007", 
     "screen_name": "MrhobanJames", 
     "name": "Hobnob"
    }, 
    {
     "id": 3434540242, 
     "indices": [
      52, 
      62
     ], 
     "id_str": "3434540242", 
     "screen_name": "Husker_Ju", 
     "name": "J. C. Gawn"
    }, 
    {
     "id": 21305022, 
     "indices": [
      63, 
      74
     ], 
     "id_str": "21305022", 
     "screen_name": "alexrubner", 
     "name": "(((Rubie)))"
    }, 
    {
     "id": 231494207, 
     "indices": [
      75, 
      87
     ], 
     "id_str": "231494207", 
     "screen_name": "jobellerina", 
     "name": "Joanne Bell"
    }, 
    {
     "id": 989964638233284615, 
     "indices": [
      88, 
      101
     ], 
     "id_str": "989964638233284615", 
     "screen_name": "moose_malloy", 
     "name": "tom"
    }, 
    {
     "id": 1628552390, 
     "indices": [
      102, 
      111
     ], 
     "id_str": "1628552390", 
     "screen_name": "AbiWilks", 
     "name": "Abi"
    }
   ], 
   "hashtags": [], 
   "urls": [
    {
     "url": "https://t.co/UH4m34f66y", 
     "indices": [
      113, 
      136
     ], 
     "expanded_url": "https://twitter.com/i/web/status/1106175236192391168", 
     "display_url": "twitter.com/i/web/status/1\u2026"
    }
   ]
  }, 
  "Geo": null
 }
}